{
    "version": "5.8.1",
    "flags": {},
    "shapes": [
        {
            "label": "turtlebot",
            "points": [
                [
                    187.49504950495052,
                    112.84158415841584
                ],
                [
                    83.5231095161918,
                    -1.4210854715202004e-14
                ]
            ],
            "group_id": null,
            "description": "",
            "shape_type": "rectangle",
            "flags": {},
            "mask": null
        }
    ],
    "imagePath": "img_000185.png",
    "imageData": null,
    "imageHeight": 244,
    "imageWidth": 324
}