{
    "version": "5.8.1",
    "flags": {},
    "shapes": [
        {
            "label": "turtlebot",
            "points": [
                [
                    172.14851485148515,
                    242.54455445544554
                ],
                [
                    26.60396039603961,
                    168.78217821782178
                ]
            ],
            "group_id": null,
            "description": "",
            "shape_type": "rectangle",
            "flags": {},
            "mask": null
        }
    ],
    "imagePath": "img_000121.png",
    "imageData": null,
    "imageHeight": 244,
    "imageWidth": 324
}