{
    "version": "5.8.1",
    "flags": {},
    "shapes": [
        {
            "label": "turtlebot",
            "points": [
                [
                    248.8811881188119,
                    227.1980198019802
                ],
                [
                    137.49504950495052,
                    96.5049504950495
                ]
            ],
            "group_id": null,
            "description": "",
            "shape_type": "rectangle",
            "flags": {},
            "mask": null
        }
    ],
    "imagePath": "img_000053.png",
    "imageData": null,
    "imageHeight": 244,
    "imageWidth": 324
}