{
    "version": "5.8.1",
    "flags": {},
    "shapes": [
        {
            "label": "turtlebot",
            "points": [
                [
                    35.019801980198025,
                    16.801980198019802
                ],
                [
                    165.21782178217822,
                    193.5346534653465
                ]
            ],
            "group_id": null,
            "description": "",
            "shape_type": "rectangle",
            "flags": {},
            "mask": null
        }
    ],
    "imagePath": "img_000052.png",
    "imageData": null,
    "imageHeight": 244,
    "imageWidth": 324
}