{
    "version": "5.8.1",
    "flags": {},
    "shapes": [
        {
            "label": "turtlebot",
            "points": [
                [
                    175.11881188118812,
                    50.46534653465346
                ],
                [
                    66.20792079207922,
                    194.5247524752475
                ]
            ],
            "group_id": null,
            "description": "",
            "shape_type": "rectangle",
            "flags": {},
            "mask": null
        }
    ],
    "imagePath": "img_000073.png",
    "imageData": null,
    "imageHeight": 244,
    "imageWidth": 324
}