{
    "version": "5.8.1",
    "flags": {},
    "shapes": [
        {
            "label": "turtlebot",
            "points": [
                [
                    2.841584158415845,
                    39.07920792079208
                ],
                [
                    148.3861386138614,
                    222.24752475247524
                ]
            ],
            "group_id": null,
            "description": "",
            "shape_type": "rectangle",
            "flags": {},
            "mask": null
        }
    ],
    "imagePath": "img_000056.png",
    "imageData": null,
    "imageHeight": 244,
    "imageWidth": 324
}